apdu_fuzzer
