Metadata-Version: 2.1
Name: apdu-fuzzer
Version: 0.0.3
Summary: APDU fuzzer
Home-page: https://github.com/petrs/APDUFuzzer
Author: Petr Svenda
Author-email: svenda@fi.muni.cz
License: MIT
Platform: UNKNOWN
Classifier: Development Status :: 3 - Alpha
Classifier: Intended Audience :: Developers
Classifier: Programming Language :: Python
Classifier: Programming Language :: Python :: 2.6
Classifier: Programming Language :: Python :: 2.7
Classifier: Programming Language :: Python :: 3.5
Classifier: Programming Language :: Python :: 3.6
Classifier: Topic :: Security
Provides-Extra: afl
Provides-Extra: dev
